move_jismeshcode/__init__.py
move_jismeshcode/move.py
move_jismeshcode/sub.py
move_jismeshcode/test_move.py
move_jismeshcode/test_sub.py
move_jismeshcode-0.0.5.dist-info/LICENSE
move_jismeshcode-0.0.5.dist-info/METADATA
move_jismeshcode-0.0.5.dist-info/WHEEL
move_jismeshcode-0.0.5.dist-info/top_level.txt
move_jismeshcode-0.0.5.dist-info/RECORD
