Metadata-Version: 2.1
Name: move-jismeshcode
Version: 0.0.5
Summary: return new JIS meshcode that moves (x, y)
Home-page: http://github.com/igtm/move_jismeshcode
Author: igtm
Author-email: tomo14916253@yahoo.co.jp
License: MIT
Keywords: meshcode,jis
Platform: UNKNOWN
Classifier: Development Status :: 3 - Alpha
Classifier: License :: OSI Approved :: MIT License
Classifier: Programming Language :: Python :: 3
Classifier: Programming Language :: Python :: 3.2
Classifier: Programming Language :: Python :: 3.3
Classifier: Programming Language :: Python :: 3.4
Classifier: Programming Language :: Python :: 3.5
Classifier: Programming Language :: Python :: 3.6
Classifier: Programming Language :: Python :: 3.7
Classifier: Programming Language :: Python :: 3.8
Classifier: Programming Language :: Python :: 3.9
License-File: LICENSE
